{"propertiesBar":{"properties":[{"name":"Timeline","expanded":true,"children":[{"name":"Ease properties","expanded":true,"children":[]}]},{"name":"Time","expanded":true,"children":[{"name":"Step","expanded":true,"children":[]}]},{"name":"Miscellaneous","expanded":true,"children":[]},{"name":"Editor","expanded":true,"children":[]}],"scrollPosition":0},"visible":true,"locked":false,"expanded":true,"showUIElements":true,"timelineElementsCollections":[{"indexes":[2,6,7],"properties":{"properties":[{"name":"Common timeline properties","expanded":true,"children":[]}],"scrollPosition":0}},{"indexes":[2,3,6,7],"properties":{"properties":[{"name":"Common timeline properties","expanded":true,"children":[]}],"scrollPosition":0}},{"indexes":[3,4,7],"properties":{"properties":[{"name":"Common timeline properties","expanded":true,"children":[]}],"scrollPosition":0}},{"indexes":[1,6],"properties":{"properties":[{"name":"Common timeline properties","expanded":true,"children":[]}],"scrollPosition":0}},{"indexes":[5,6],"properties":{"properties":[{"name":"Common timeline properties","expanded":true,"children":[]}],"scrollPosition":0}},{"indexes":[0,6],"properties":{"properties":[{"name":"Common timeline properties","expanded":true,"children":[]}],"scrollPosition":0}},{"indexes":[6],"properties":{"properties":[{"name":"Common timeline properties","expanded":true,"children":[]}],"scrollPosition":0}},{"indexes":[6],"properties":{"properties":[{"name":"Common timeline properties","expanded":true,"children":[]}],"scrollPosition":0}},{"indexes":[0],"properties":{"properties":[{"name":"Common timeline properties","expanded":true,"children":[]}],"scrollPosition":0}}],"tracks":[{"keyframes":[{"time":0,"tags":"","propertiesBar":{},"visible":true,"locked":false,"expanded":true,"showUIElements":true,"timelineElementsCollections":[]},{"time":2.5,"tags":"","propertiesBar":{},"visible":true,"locked":false,"expanded":true,"showUIElements":true,"timelineElementsCollections":[]},{"time":5.7,"tags":"","propertiesBar":{},"visible":true,"locked":false,"expanded":true,"showUIElements":true,"timelineElementsCollections":[]},{"time":9,"tags":"","propertiesBar":{},"visible":true,"locked":false,"expanded":true,"showUIElements":true,"timelineElementsCollections":[]}],"propertyTracks":[{"property":"text","source":{"type":"plugin","uid":"Spritefont2"},"propertiesBar":{},"visible":true,"locked":false,"expanded":true,"showUIElements":true,"timelineElementsCollections":[],"propertyKeyframes":[{"time":0,"propertiesBar":{"properties":[{"name":"Property keyframe","expanded":true,"children":[{"name":"Ease properties","expanded":true,"children":[]}]}],"scrollPosition":0},"visible":true,"locked":false,"expanded":true,"showUIElements":true,"timelineElementsCollections":[]},{"time":2.5,"propertiesBar":{},"visible":true,"locked":false,"expanded":true,"showUIElements":true,"timelineElementsCollections":[]},{"time":5.7,"propertiesBar":{},"visible":true,"locked":false,"expanded":true,"showUIElements":true,"timelineElementsCollections":[]},{"time":9,"propertiesBar":{},"visible":true,"locked":false,"expanded":true,"showUIElements":true,"timelineElementsCollections":[]}]}],"propertyTracksRoot":{"name":"Property Track Folder","items":[],"subfolders":[],"propertiesBar":{},"visible":true,"locked":false,"expanded":true,"showUIElements":true,"timelineElementsCollections":[]},"type":"instance-track","worldInstance":11,"objectType":"SpriteFont","project":"jylnef8x06j","propertiesBar":{},"visible":true,"locked":false,"expanded":true,"showUIElements":true,"timelineElementsCollections":[]}],"tracksRoot":{"propertiesBar":{},"visible":true,"locked":false,"expanded":true,"showUIElements":true,"timelineElementsCollections":[],"name":"Track Folder","items":[],"subfolders":[]},"nestedTimelinesRoot":{"propertiesBar":{},"visible":true,"locked":false,"expanded":true,"showUIElements":true,"timelineElementsCollections":[],"name":"Timelines","subfolders":[]}}