{
	"name": "Player",
	"plugin-id": "Sprite",
	"sid": 792667009531476,
	"isGlobal": false,
	"instanceVariables": [],
	"behaviorTypes": [
		{
			"behaviorId": "EightDir",
			"name": "8Direction",
			"sid": 266410544150608
		}
	],
	"effectTypes": [],
	"animations": {
		"items": [
			{
				"frames": [
					{
						"width": 250,
						"height": 250,
						"originX": 0.5,
						"originY": 0.5,
						"originalSource": "",
						"exportFormat": "lossless",
						"exportQuality": 0.8,
						"imageSpriteId": 7121919,
						"collisionPoly": {
							"points": [
								1,
								0,
								1,
								1,
								0,
								1,
								0,
								0
							]
						},
						"useCollisionPoly": true,
						"duration": 1
					}
				],
				"sid": 619630537849627,
				"name": "Animation 1",
				"isLooping": false,
				"isPingPong": false,
				"repeatCount": 1,
				"repeatTo": 0,
				"speed": 5
			}
		],
		"subfolders": []
	}
}